robotframework_seleniumlibrary_translation_fi/__init__.py
robotframework_seleniumlibrary_translation_fi/translation.json
robotframework_seleniumlibrary_translation_fi-0.2.0.dist-info/LICENSE
robotframework_seleniumlibrary_translation_fi-0.2.0.dist-info/METADATA
robotframework_seleniumlibrary_translation_fi-0.2.0.dist-info/WHEEL
robotframework_seleniumlibrary_translation_fi-0.2.0.dist-info/top_level.txt
robotframework_seleniumlibrary_translation_fi-0.2.0.dist-info/RECORD
