Metadata-Version: 2.2
Name: robotframework-seleniumlibrary-translation-fi
Version: 0.2.0
Summary: Robot Framework SeleniumLibrary translation to Finnish languege
Author-email: Tatu Aalto <aalto.tatu@gmail.com>
License:                                  Apache License
Project-URL: Homepage, https://github.com/MarketSquare/robotframework-seleniumlibrary-translation-fi
Project-URL: Issues, https://github.com/MarketSquare/robotframework-seleniumlibrary-translation-fi/issues
Project-URL: Changelog, https://github.com/MarketSquare/robotframework-seleniumlibrary-translation-fi/blob/main/CHANGELOG.md
Keywords: Robot Framework,SeleniumLibrary
Classifier: Development Status :: 5 - Production/Stable
Classifier: Framework :: Robot Framework :: Library
Classifier: Topic :: Software Development :: Testing :: Acceptance
Classifier: Programming Language :: Python :: 3
Classifier: Programming Language :: Python :: 3.8
Classifier: Programming Language :: Python :: 3.9
Classifier: Programming Language :: Python :: 3.10
Classifier: Programming Language :: Python :: 3.11
Classifier: Programming Language :: Python :: 3.12
Classifier: License :: OSI Approved :: Apache Software License
Classifier: Operating System :: OS Independent
Requires-Python: >=3.8
License-File: LICENSE
Requires-Dist: robotframework-seleniumlibrary>=6.7.0
